{
    "comments": [
        "FAIL due to 2304 bad strips (more than 15)",
        "FAIL due to 1152 consecutive bad strips (more than 8)",
        "No trim data found",
        "No RC data found"
    ],
    "date": "2023-05-23T13:25:09.000Z",
    "defects": [
        {
            "description": "High Noise occupancy > 0.000500",
            "name": "NO_HI",
            "properties": {
                "chip_bank": "under",
                "chip_in_histo": 2
            }
        },
        {
            "description": "High Noise occupancy > 0.000500",
            "name": "NO_HI",
            "properties": {
                "chip_bank": "under",
                "chip_in_histo": 3
            }
        },
        {
            "description": "High Noise occupancy > 0.000500",
            "name": "NO_HI",
            "properties": {
                "chip_bank": "under",
                "chip_in_histo": 4
            }
        },
        {
            "description": "High Noise occupancy > 0.000500",
            "name": "NO_HI",
            "properties": {
                "chip_bank": "under",
                "chip_in_histo": 5
            }
        },
        {
            "description": "High Noise occupancy > 0.000500",
            "name": "NO_HI",
            "properties": {
                "chip_bank": "under",
                "chip_in_histo": 6
            }
        },
        {
            "description": "High Noise occupancy > 0.000500",
            "name": "NO_HI",
            "properties": {
                "chip_bank": "under",
                "chip_in_histo": 7
            }
        },
        {
            "description": "High Noise occupancy > 0.000500",
            "name": "NO_HI",
            "properties": {
                "chip_bank": "under",
                "chip_in_histo": 8
            }
        },
        {
            "description": "High Noise occupancy > 0.000500",
            "name": "NO_HI",
            "properties": {
                "chip_bank": "under",
                "chip_in_histo": 9
            }
        },
        {
            "description": "High Noise occupancy > 0.000500",
            "name": "NO_HI",
            "properties": {
                "chip_bank": "under",
                "chip_in_histo": 10
            }
        },
        {
            "description": "High Noise occupancy > 0.000500",
            "name": "NO_HI",
            "properties": {
                "chip_bank": "away",
                "chip_in_histo": 2
            }
        },
        {
            "description": "High Noise occupancy > 0.000500",
            "name": "NO_HI",
            "properties": {
                "chip_bank": "away",
                "chip_in_histo": 3
            }
        },
        {
            "description": "High Noise occupancy > 0.000500",
            "name": "NO_HI",
            "properties": {
                "chip_bank": "away",
                "chip_in_histo": 4
            }
        },
        {
            "description": "High Noise occupancy > 0.000500",
            "name": "NO_HI",
            "properties": {
                "chip_bank": "away",
                "chip_in_histo": 5
            }
        },
        {
            "description": "High Noise occupancy > 0.000500",
            "name": "NO_HI",
            "properties": {
                "chip_bank": "away",
                "chip_in_histo": 6
            }
        },
        {
            "description": "High Noise occupancy > 0.000500",
            "name": "NO_HI",
            "properties": {
                "chip_bank": "away",
                "chip_in_histo": 7
            }
        },
        {
            "description": "High Noise occupancy > 0.000500",
            "name": "NO_HI",
            "properties": {
                "chip_bank": "away",
                "chip_in_histo": 8
            }
        },
        {
            "description": "High Noise occupancy > 0.000500",
            "name": "NO_HI",
            "properties": {
                "chip_bank": "away",
                "chip_in_histo": 9
            }
        },
        {
            "description": "High Noise occupancy > 0.000500",
            "name": "NO_HI",
            "properties": {
                "chip_bank": "away",
                "chip_in_histo": 10
            }
        }
    ],
    "passed": false,
    "problems": false,
    "properties": {
        "DCS": {
            "ABC_temp_raw_10": 2331.0,
            "ABC_temp_raw_2": 2267.0,
            "ABC_temp_raw_3": 2316.0,
            "ABC_temp_raw_4": 2469.0,
            "ABC_temp_raw_5": 2378.0,
            "ABC_temp_raw_6": 2361.0,
            "ABC_temp_raw_7": 2275.0,
            "ABC_temp_raw_8": 2444.0,
            "ABC_temp_raw_9": 2430.0,
            "HCC_temp_raw": 413.0,
            "HCC_temp_rough_cal": 25.092987060546875
        },
        "det_info": {
            "ABC_Fuse": [
                null,
                null,
                "894068d3",
                "894068d4",
                "894068d5",
                "894068cc",
                "894068cb",
                "894068ca",
                "894068c9",
                "894068c7",
                "894068c6"
            ],
            "Address": [
                null,
                null,
                8,
                7,
                6,
                5,
                4,
                3,
                2,
                1,
                0
            ],
            "Channel": [
                null,
                null,
                2,
                3,
                4,
                5,
                6,
                7,
                8,
                9,
                10
            ],
            "DUT_type": "ABCStar_Test     #FMC-DP connec",
            "HCC_Fuse": "30007218",
            "name": "ABCStar_R0H1_V1_M1"
        },
        "scan_info": {
            "event_count": 248,
            "rc_fit": [
                [
                    0.0,
                    0.0,
                    0.0
                ],
                [
                    0.0,
                    0.0,
                    0.0
                ],
                [
                    0.0,
                    0.0,
                    0.0
                ],
                [
                    0.0,
                    0.0,
                    0.0
                ],
                [
                    0.0,
                    0.0,
                    0.0
                ],
                [
                    0.0,
                    0.0,
                    0.0
                ],
                [
                    0.0,
                    0.0,
                    0.0
                ],
                [
                    0.0,
                    0.0,
                    0.0
                ],
                [
                    0.0,
                    0.0,
                    0.0
                ],
                [
                    0.0,
                    0.0,
                    0.0
                ],
                [
                    0.0,
                    0.0,
                    0.0
                ],
                [
                    0.0,
                    0.0,
                    0.0
                ],
                [
                    0.0,
                    0.0,
                    0.0
                ],
                [
                    0.0,
                    0.0,
                    0.0
                ],
                [
                    0.0,
                    0.0,
                    0.0
                ],
                [
                    0.0,
                    0.0,
                    0.0
                ],
                [
                    0.0,
                    0.0,
                    0.0
                ],
                [
                    0.0,
                    0.0,
                    0.0
                ],
                [
                    0.0,
                    0.0,
                    0.0
                ],
                [
                    0.0,
                    0.0,
                    0.0
                ],
                [
                    0.0,
                    0.0,
                    0.0
                ],
                [
                    0.0,
                    0.0,
                    0.0
                ]
            ],
            "rc_func": [
                0,
                0,
                0,
                0,
                0,
                0,
                0,
                0,
                0,
                0,
                0,
                0,
                0,
                0,
                0,
                0,
                0,
                0,
                0,
                0,
                0,
                0
            ],
            "trim_target": [
                15.0,
                15.0,
                15.0,
                15.0,
                15.0,
                15.0,
                15.0,
                15.0,
                15.0,
                15.0,
                15.0,
                15.0,
                15.0,
                15.0,
                15.0,
                15.0,
                15.0,
                15.0,
                15.0,
                15.0,
                15.0,
                15.0
            ]
        },
        "system_info": {
            "Analysis_time": "2023-05-23T13:25:10.000Z",
            "Firmware revision": "0xb5fb",
            "GIT URL": "https://gitlab.cern.ch/atlas-itk-strips-daq/itsdaq-sw.git/-/tree/bda0da3af762da1f207d7d1617b976f2d82f0bc2",
            "GIT branch": "",
            "GIT build date": "2023-03-31 14:47:43 +0000 (Fri, 31 Mar 2023)",
            "GIT commit date": "2023-02-07 10:39:11 +0000 (Tue, 07 Feb 2023)",
            "GIT describe": "itsdaq_28_6_2022-501-gbda0da3",
            "GIT modified": "locally modified",
            "GIT revision": "bda0da3af762da1f207d7d1617b976f2d82f0bc2",
            "Location": "LUND_COLDBOX",
            "User": "EWAL",
            "analysis_version": "3.43",
            "dedication": "New dedication as we're going for PPA",
            "host": "itkdaq"
        }
    },
    "results": {
        "enc_est_away": [
            126824.6015625,
            135652.875,
            146785.515625,
            158080.796875,
            257743.28125,
            392875.71875,
            null,
            null,
            null
        ],
        "enc_est_under": [
            121149.6484375,
            131971.15625,
            133144.515625,
            142515.234375,
            254816.25,
            208959.65625,
            239926.84375,
            217274.734375,
            null
        ],
        "occupancy_mean_away": [
            0.3994767665863037,
            0.39730316400527954,
            0.40127232670783997,
            0.40328845381736755,
            0.4004533290863037,
            0.4017133116722107,
            0.4052101969718933,
            0.40133532881736755,
            0.40703725814819336
        ],
        "occupancy_mean_under": [
            0.4019969701766968,
            0.3995712697505951,
            0.4038555324077606,
            0.40439102053642273,
            0.39824816584587097,
            0.40382400155067444,
            0.40584009885787964,
            0.4000752568244934,
            0.4081713557243347
        ],
        "occupancy_rms_away": [
            0.0077132307924330235,
            0.008402951061725616,
            0.010715685784816742,
            0.008959649130702019,
            0.00871188472956419,
            0.007792146410793066,
            0.007198947481811047,
            0.008000267669558525,
            0.007845896296203136
        ],
        "occupancy_rms_under": [
            0.009610487148165703,
            0.008380246348679066,
            0.007567824795842171,
            0.008207404054701328,
            0.009093335829675198,
            0.009670191444456577,
            0.007174090016633272,
            0.008157500065863132,
            0.008331251330673695
        ],
        "offset_away": [
            467.2221984863281,
            595.8875122070313,
            846.1665649414063,
            1148.956787109375,
            3384.411865234375,
            6688239.5,
            12658767.0,
            1473536.875,
            2709633.0
        ],
        "offset_under": [
            380.1744689941406,
            530.6192016601563,
            544.089599609375,
            609.193603515625,
            2900.075927734375,
            11132.4775390625,
            3982988.0,
            1889.966064453125,
            2723951.75
        ]
    },
    "runNumber": "101-27",
    "testType": "NO_PPA"
}
