{
    "date": "2024-01-18T18:40:23.000Z",
    "defects": [
        {
            "description": "High SD width: -6.4 (module average -19188626.0)",
            "name": "SD_HIGH_WIDTH",
            "properties": {
                "chip_bank": "under",
                "chip_in_histo": 0
            }
        },
        {
            "description": "Empty bins (2)",
            "name": "SD_EMPTY",
            "properties": {
                "chip_bank": "under",
                "chip_in_histo": 1
            }
        },
        {
            "description": "High SD width: 4.8 (module average -19188626.0)",
            "name": "SD_HIGH_WIDTH",
            "properties": {
                "chip_bank": "under",
                "chip_in_histo": 1
            }
        },
        {
            "description": "High SD width: -27.3 (module average -19188626.0)",
            "name": "SD_HIGH_WIDTH",
            "properties": {
                "chip_bank": "under",
                "chip_in_histo": 2
            }
        },
        {
            "description": "Empty bins (4)",
            "name": "SD_EMPTY",
            "properties": {
                "chip_bank": "under",
                "chip_in_histo": 3
            }
        },
        {
            "description": "High SD width: 7.1 (module average -19188626.0)",
            "name": "SD_HIGH_WIDTH",
            "properties": {
                "chip_bank": "under",
                "chip_in_histo": 3
            }
        },
        {
            "description": "High SD width: -8.0 (module average -19188626.0)",
            "name": "SD_HIGH_WIDTH",
            "properties": {
                "chip_bank": "under",
                "chip_in_histo": 4
            }
        },
        {
            "description": "High SD width: -155.8 (module average -19188626.0)",
            "name": "SD_HIGH_WIDTH",
            "properties": {
                "chip_bank": "under",
                "chip_in_histo": 5
            }
        },
        {
            "description": "High SD width: -3.6 (module average -19188626.0)",
            "name": "SD_HIGH_WIDTH",
            "properties": {
                "chip_bank": "under",
                "chip_in_histo": 6
            }
        },
        {
            "description": "High SD width: -1979976.6 (module average -19188626.0)",
            "name": "SD_HIGH_WIDTH",
            "properties": {
                "chip_bank": "under",
                "chip_in_histo": 7
            }
        },
        {
            "description": "Empty bins (9)",
            "name": "SD_EMPTY",
            "properties": {
                "chip_bank": "under",
                "chip_in_histo": 8
            }
        },
        {
            "description": "High Fall: 61.3",
            "name": "SD_HIGH_FALL_MINOR",
            "properties": {
                "chip_bank": "under",
                "chip_in_histo": 8
            }
        },
        {
            "description": "High SD width: 11.6 (module average -19188626.0)",
            "name": "SD_HIGH_WIDTH",
            "properties": {
                "chip_bank": "under",
                "chip_in_histo": 8
            }
        },
        {
            "description": "Empty bins (5)",
            "name": "SD_EMPTY",
            "properties": {
                "chip_bank": "under",
                "chip_in_histo": 9
            }
        },
        {
            "description": "High SD width: 8.0 (module average -19188626.0)",
            "name": "SD_HIGH_WIDTH",
            "properties": {
                "chip_bank": "under",
                "chip_in_histo": 9
            }
        },
        {
            "description": "High SD width: -44155.0 (module average -19188626.0)",
            "name": "SD_HIGH_WIDTH",
            "properties": {
                "chip_bank": "away",
                "chip_in_histo": 0
            }
        },
        {
            "description": "High SD width: -27.1 (module average -19188626.0)",
            "name": "SD_HIGH_WIDTH",
            "properties": {
                "chip_bank": "away",
                "chip_in_histo": 1
            }
        },
        {
            "description": "High SD width: -35.7 (module average -19188626.0)",
            "name": "SD_HIGH_WIDTH",
            "properties": {
                "chip_bank": "away",
                "chip_in_histo": 2
            }
        },
        {
            "description": "High SD width: -31470.7 (module average -19188626.0)",
            "name": "SD_HIGH_WIDTH",
            "properties": {
                "chip_bank": "away",
                "chip_in_histo": 3
            }
        },
        {
            "description": "High SD width: -359715.3 (module average -19188626.0)",
            "name": "SD_HIGH_WIDTH",
            "properties": {
                "chip_bank": "away",
                "chip_in_histo": 4
            }
        },
        {
            "description": "High SD width: -18.1 (module average -19188626.0)",
            "name": "SD_HIGH_WIDTH",
            "properties": {
                "chip_bank": "away",
                "chip_in_histo": 5
            }
        },
        {
            "description": "Low SD width: -25134650.0 (module average -19188626.0)",
            "name": "SD_LOW_WIDTH",
            "properties": {
                "chip_bank": "away",
                "chip_in_histo": 6
            }
        },
        {
            "description": "Empty bins (2)",
            "name": "SD_EMPTY",
            "properties": {
                "chip_bank": "away",
                "chip_in_histo": 7
            }
        },
        {
            "description": "High SD width: 2.3 (module average -19188626.0)",
            "name": "SD_HIGH_WIDTH",
            "properties": {
                "chip_bank": "away",
                "chip_in_histo": 7
            }
        },
        {
            "description": "Low Rise 258890768.0",
            "name": "SD_LOW_RISE_MINOR",
            "properties": {
                "chip_bank": "away",
                "chip_in_histo": 8
            }
        },
        {
            "description": "Low SD width: -258890704.0 (module average -19188626.0)",
            "name": "SD_LOW_WIDTH",
            "properties": {
                "chip_bank": "away",
                "chip_in_histo": 8
            }
        },
        {
            "description": "High SD width: -1388402.0 (module average -19188626.0)",
            "name": "SD_HIGH_WIDTH",
            "properties": {
                "chip_bank": "away",
                "chip_in_histo": 9
            }
        }
    ],
    "institution": "LUND",
    "passed": false,
    "problems": true,
    "properties": {
        "DCS": {
            "LV Module 1_LV_current": 50.0,
            "LV Module 1_LV_voltage": 11000.0
        },
        "FRACTION": 0.57,
        "det_info": {
            "Address": [
                0,
                1,
                2,
                3,
                4,
                5,
                6,
                7,
                8,
                9
            ],
            "DUT_type": "Barrel",
            "LV Module 1_LV_model": "72-2710",
            "LV Module 1_LV_serial": "V2.5",
            "ccr_identifier": "0",
            "daq_stream": "8",
            "name": "star_barrel_LS_X_chipset_10"
        },
        "scan_info": {
            "event_count": [
                7,
                7,
                7,
                7,
                7,
                7,
                8,
                7,
                7,
                7,
                7,
                7,
                8,
                7,
                7,
                7,
                7,
                7,
                8,
                8,
                7,
                7,
                7,
                8,
                7,
                7,
                7,
                7,
                7,
                7,
                7,
                8,
                7,
                7,
                7,
                7,
                7,
                7,
                7,
                8,
                7,
                7,
                7,
                7,
                8,
                7,
                9,
                9,
                7,
                7,
                7,
                8,
                7,
                7,
                8,
                7,
                7,
                7,
                7,
                7,
                8,
                7,
                8,
                8
            ]
        },
        "system_info": {
            "Analysis_time": "2024-01-18T18:40:24.000Z",
            "Firmware revision": "0xb5fb",
            "GIT URL": "https://gitlab.cern.ch/atlas-itk-strips-daq/itsdaq-sw.git/-/tree/70018b79248f486e912e4a7487f320ce83eeed24",
            "GIT branch": "",
            "GIT build date": "2024-01-18 15:50:47 +0000 (Thu, 18 Jan 2024)",
            "GIT commit date": "2024-01-17 13:29:11 +0000 (Wed, 17 Jan 2024)",
            "GIT describe": "itsdaq_23_3_2023-1044-g70018b792",
            "GIT modified": "locally modified",
            "GIT revision": "70018b79248f486e912e4a7487f320ce83eeed24",
            "Location": "COLDBOX",
            "User": "EWAL",
            "analysis_version": "3.43",
            "dedication": "New dedication as we're going for PPA",
            "host": "itkdaq"
        }
    },
    "results": {
        "StrobeDelay_away": [
            25118,
            67,
            75,
            17869,
            154733,
            64,
            10807958,
            22,
            111323062,
            578366,
            -1,
            -1,
            -1,
            -1,
            -1,
            -1
        ],
        "StrobeDelay_under": [
            56,
            53,
            67,
            53,
            58,
            121,
            57,
            1128572,
            56,
            55,
            -1,
            -1,
            -1,
            -1,
            -1,
            -1
        ]
    },
    "runNumber": "386-1",
    "testType": "STROBE_DELAY_PPA"
}
