{
    "component": "ABCStar_R5H1_ppa",
    "date": "2024-04-04T13:43:37.000Z",
    "institution": "LUND",
    "passed": true,
    "problems": false,
    "properties": {
        "AMAC_CURRENT_RANGE": [
            0,
            0,
            0,
            0,
            0,
            0,
            0,
            0,
            0,
            0,
            0,
            0,
            0,
            0,
            0,
            0,
            0,
            0,
            0,
            0,
            0,
            0,
            0,
            0,
            0,
            0,
            0,
            0,
            0,
            0,
            0,
            0,
            0,
            0,
            0,
            0,
            0,
            0,
            0,
            0,
            0,
            0,
            0,
            0,
            0,
            0,
            0,
            0,
            0,
            0,
            0,
            0,
            0,
            0,
            0,
            0,
            0,
            0,
            0
        ],
        "AMAC_READINGS": 1000,
        "det_info": {
            "AMAC_FuseID": "000000",
            "ccr_identifier": "0",
            "daq_stream": "34",
            "name": "ABCStar_R5H1_ppa"
        },
        "scan_info": {
            "AMAC_ILIMIT": 10,
            "PS_ILIMIT": 10,
            "RAMP_DELAY_MS": 10000,
            "SET_VOLTAGE": [
                0.0,
                -10.0,
                -20.0,
                -30.0,
                -40.0,
                -50.0,
                -60.0,
                -70.0,
                -80.0,
                -90.0,
                -100.0,
                -110.0,
                -120.0,
                -130.0,
                -140.0,
                -150.0,
                -160.0,
                -170.0,
                -180.0,
                -190.0,
                -200.0,
                -210.0,
                -220.0,
                -230.0,
                -240.0,
                -250.0,
                -260.0,
                -270.0,
                -280.0,
                -290.0,
                -300.0,
                -310.0,
                -320.0,
                -330.0,
                -340.0,
                -350.0,
                -360.0,
                -370.0,
                -380.0,
                -390.0,
                -400.0,
                -410.0,
                -420.0,
                -430.0,
                -440.0,
                -450.0,
                -460.0,
                -470.0,
                -480.0,
                -490.0,
                -500.0,
                -510.0,
                -520.0,
                -530.0,
                -540.0,
                -550.0,
                -550.0,
                -550.0,
                -550.0
            ]
        },
        "sensor_type": "R5",
        "system_info": {
            "Firmware revision": "0xb5fb",
            "GIT URL": "https://gitlab.cern.ch/atlas-itk-strips-daq/itsdaq-sw.git/-/tree/72e5caf3069869ba786876f5d371d3a5b9cf573f",
            "GIT branch": "",
            "GIT build date": "2024-02-08 10:23:47 +0000 (Thu, 08 Feb 2024)",
            "GIT commit date": "2024-02-07 11:14:27 +0000 (Wed, 07 Feb 2024)",
            "GIT describe": "itsdaq_23_3_2023-1125-g72e5caf30",
            "GIT revision": "72e5caf3069869ba786876f5d371d3a5b9cf573f",
            "analysis_version": "3.43",
            "dedication": "New dedication as we're going for PPA"
        }
    },
    "results": {
        "CURRENT": [
            93.83597564697266,
            -357.2957763671875,
            -396.18017578125,
            -418.07464599609375,
            -374.48529052734375,
            -415.1561279296875,
            -428.31903076171875,
            -517.7422485351563,
            -631.212158203125,
            -691.3128662109375,
            -768.48486328125,
            -812.771728515625,
            -883.638671875,
            -939.5366821289063,
            -893.7759399414063,
            -877.6743774414063,
            -911.5459594726563,
            -979.9530029296875,
            -1005.0787353515625,
            -1012.9653930664063,
            -1017.8510131835938,
            -1047.41748046875,
            -1038.7257080078125,
            -1063.0167236328125,
            -1091.5628662109375,
            -1086.3602294921875,
            -1060.8494873046875,
            -1066.3448486328125,
            -1014.0888671875,
            -999.992919921875,
            -993.5551147460938,
            -984.1253662109375,
            -971.626708984375,
            -1012.1892700195313,
            -1013.9368896484375,
            -1005.5037841796875,
            -951.897705078125,
            -955.4963989257813,
            -976.7559204101563,
            -971.2657470703125,
            -922.1316528320313,
            -912.4295654296875,
            -912.60986328125,
            -916.641845703125,
            -941.9519653320313,
            -934.1681518554688,
            -920.9756469726563,
            -912.2098388671875,
            -908.6615600585938,
            -894.2052001953125,
            -894.927001953125,
            -879.4609375,
            -877.4011840820313,
            -875.0631713867188,
            -872.8328857421875,
            -868.7816772460938,
            -874.8236083984375,
            -864.3453979492188,
            -879.953857421875
        ],
        "CURRENT_RMS": [
            7.816962242126465,
            7.659114360809326,
            7.846199989318848,
            8.211416244506836,
            8.061396598815918,
            7.946070671081543,
            7.378114700317383,
            7.314301490783691,
            6.776904106140137,
            6.762247562408447,
            6.705209732055664,
            6.743077754974365,
            6.083279609680176,
            6.073830604553223,
            6.828493118286133,
            6.757136344909668,
            6.807684421539307,
            6.168394565582275,
            6.176651477813721,
            6.327576160430908,
            5.942895889282227,
            6.1105451583862305,
            5.880632400512695,
            5.66196870803833,
            5.278070449829102,
            5.601658344268799,
            5.383290767669678,
            5.229426383972168,
            5.670713424682617,
            5.617403507232666,
            5.997073650360107,
            5.597856044769287,
            5.568215370178223,
            5.47377872467041,
            5.099226951599121,
            5.3709716796875,
            5.594075679779053,
            5.437995910644531,
            5.268893718719482,
            5.459979057312012,
            5.470911026000977,
            5.313531875610352,
            5.390294075012207,
            5.571764945983887,
            5.1648454666137695,
            5.2115983963012695,
            5.151382923126221,
            5.155069351196289,
            5.14876127243042,
            5.2064337730407715,
            5.337523460388184,
            5.425337314605713,
            5.216144561767578,
            5.2019476890563965,
            5.187472343444824,
            5.029523849487305,
            5.047195911407471,
            5.371671199798584,
            5.348971843719482
        ],
        "HUMIDITY": 2.0,
        "I_500V": 10.560322761535645,
        "PS_CURRENT": [
            0.0,
            2.1979000568389893,
            4.34660005569458,
            6.492300033569336,
            8.638999938964844,
            10.784899711608887,
            12.927599906921387,
            15.069499969482422,
            17.20549964904785,
            19.34429931640625,
            21.48390007019043,
            23.622299194335938,
            25.767900466918945,
            27.911399841308594,
            30.050600051879883,
            32.19139862060547,
            34.33190155029297,
            36.47719955444336,
            38.62350082397461,
            40.76940155029297,
            42.919898986816406,
            45.069000244140625,
            47.21500015258789,
            49.36050033569336,
            51.508201599121094,
            53.657501220703125,
            55.81060028076172,
            57.96379852294922,
            60.11579895019531,
            62.2672004699707,
            64.41809844970703,
            66.57430267333984,
            68.73480224609375,
            70.88860321044922,
            73.04440307617188,
            75.20079803466797,
            77.3552017211914,
            79.51219940185547,
            81.67120361328125,
            83.82849884033203,
            85.98600006103516,
            88.14350128173828,
            90.30500030517578,
            92.4655990600586,
            94.61900329589844,
            96.76100158691406,
            98.93299865722656,
            101.10600280761719,
            103.28700256347656,
            105.45099639892578,
            107.63999938964844,
            109.77100372314453,
            111.96600341796875,
            114.13300323486328,
            116.3030014038086,
            118.47000122070313,
            118.47000122070313,
            118.47000122070313,
            118.47000122070313
        ],
        "TEMPERATURE": 22.0,
        "VBD": 9.990000452351092e+37,
        "VOLTAGE": [
            0.0,
            -9.9399995803833,
            -19.920000076293945,
            -29.940000534057617,
            -39.939998626708984,
            -49.939998626708984,
            -59.97999954223633,
            -70.0,
            -79.9800033569336,
            -90.04000091552734,
            -100.0,
            -110.0199966430664,
            -120.0199966430664,
            -130.02000427246094,
            -140.02000427246094,
            -150.0800018310547,
            -160.0399932861328,
            -170.02000427246094,
            -180.05999755859375,
            -190.05999755859375,
            -199.89999389648438,
            -210.10000610351563,
            -220.0800018310547,
            -230.0800018310547,
            -240.10000610351563,
            -250.10000610351563,
            -260.1199951171875,
            -270.1199951171875,
            -280.17999267578125,
            -290.1600036621094,
            -300.1600036621094,
            -309.8800048828125,
            -319.9200134277344,
            -329.9200134277344,
            -339.94000244140625,
            -349.94000244140625,
            -359.94000244140625,
            -369.9599914550781,
            -379.9200134277344,
            -389.9599914550781,
            -399.9800109863281,
            -409.9599914550781,
            -419.9599914550781,
            -429.9599914550781,
            -440.0,
            -449.9599914550781,
            -459.9599914550781,
            -469.9800109863281,
            -479.9800109863281,
            -489.9800109863281,
            -500.0199890136719,
            -510.0,
            -520.02001953125,
            -530.0,
            -540.02001953125,
            -550.02001953125,
            -550.02001953125,
            -550.02001953125,
            -550.02001953125
        ]
    },
    "runNumber": "519-1",
    "testType": "MODULE_IV_AMAC"
}
